qanat/__init__.py
qanat/decorators.py
qanat/version.py
pyqanat-0.0.0.dist-info/LICENCE
pyqanat-0.0.0.dist-info/METADATA
pyqanat-0.0.0.dist-info/WHEEL
pyqanat-0.0.0.dist-info/top_level.txt
pyqanat-0.0.0.dist-info/RECORD
