Metadata-Version: 2.1
Name: pyqanat
Version: 0.0.0
Summary: Create simple event-driven, distributed data pipelines in Python
Home-page: https://github.com/jarombouts/qanat
Author: Your Name
Author-email: 
License: MIT
Keywords: data pipelines event-driven architecture microservices mqtt
Classifier: Development Status :: 3 - Alpha
Classifier: Intended Audience :: Developers
Classifier: Topic :: Software Development :: Libraries :: Application Frameworks
Classifier: Topic :: Software Development :: Libraries :: Python Modules
Classifier: Topic :: System :: Distributed Computing
Classifier: License :: OSI Approved :: MIT License
Classifier: Programming Language :: Python :: 3
Classifier: Programming Language :: Python :: 3.11
Requires-Python: >=3.11
License-File: LICENCE
Requires-Dist: paho-mqtt (>=1.6.1)
Requires-Dist: networkx (>=3.2.1)
